{"is_source_file": false, "format": "", "description": "", "external_files": [], "external_methods": [], "published": [], "classes": [], "methods": [], "calls": [], "search-terms": [], "state": 2, "file_id": 12, "knowledge_revision": 20, "git_revision": "1a093178719ccc6462067f772e10e8a0e178e550", "hash": "9a911716a1541df12c5b16aced50c703", "format-version": 4, "code-base-name": "tic_tac_toe_frontend", "filename": "README.md", "revision_history": [{"20": "1a093178719ccc6462067f772e10e8a0e178e550"}]}